{
  "layers": [
    {
      "uri": "IPFS_CID_PLACEHOLDER/layers/45/background.png",
      "z": 0
    },
    {
      "slot": "MOON",
      "z": 10
    },
    {
      "uri": "IPFS_CID_PLACEHOLDER/layers/45/rockets.png",
      "z": 20
    },
    {
      "slot": "PASSENGER",
      "z": 30
    },
    {
      "uri": "IPFS_CID_PLACEHOLDER/layers/45/body.png",
      "z": 40
    },
    {
      "uri": "IPFS_CID_PLACEHOLDER/layers/45/face.png",
      "z": 50
    },
    {
      "uri": "IPFS_CID_PLACEHOLDER/layers/45/items.png",
      "z": 60
    }
  ],
  "traits": {
    "Background": "Invaders",
    "Rockets": "ACME",
    "Dirac Body": "Black Suit",
    "Dirac Face": "Stoned",
    "Dirac Items": "Penguin"
  }
}
