{
  "layers": [
    {
      "uri": "IPFS_CID_PLACEHOLDER/layers/87/background.png",
      "z": 0
    },
    {
      "slot": "MOON",
      "z": 10
    },
    {
      "uri": "IPFS_CID_PLACEHOLDER/layers/87/rockets.png",
      "z": 20
    },
    {
      "slot": "PASSENGER",
      "z": 30
    },
    {
      "uri": "IPFS_CID_PLACEHOLDER/layers/87/body.png",
      "z": 40
    },
    {
      "uri": "IPFS_CID_PLACEHOLDER/layers/87/face.png",
      "z": 50
    },
    {
      "uri": "IPFS_CID_PLACEHOLDER/layers/87/items.png",
      "z": 60
    }
  ],
  "traits": {
    "Background": "The Starry Night",
    "Rockets": "Plug",
    "Dirac Body": "Black Suit",
    "Dirac Face": "Stoned",
    "Dirac Items": "Pit Viper 2000"
  }
}
